LICENSE
README.md
setup.cfg
setup.py
heyWFeng/__init__.py
heyWFeng/hello-world.py
heyWFeng.egg-info/PKG-INFO
heyWFeng.egg-info/SOURCES.txt
heyWFeng.egg-info/dependency_links.txt
heyWFeng.egg-info/not-zip-safe
heyWFeng.egg-info/requires.txt
heyWFeng.egg-info/top_level.txt